identicons/__init__.py
identicons/_generate/__init__.py
identicons/cli/__init__.py
identicons-0.1.0.dist-info/METADATA
identicons-0.1.0.dist-info/WHEEL
identicons-0.1.0.dist-info/entry_points.txt
identicons-0.1.0.dist-info/top_level.txt
identicons-0.1.0.dist-info/RECORD
