Metadata-Version: 2.1
Name: identicons
Version: 0.1.0
Summary: A lightweight, easy-to-use Python package for generating unique identicons - graphical representations of hashed user information. It's perfect for adding a touch of personalization to user profiles in web applications, forums, or any platform requiring distinct visual user identification.
Home-page: https://github.com/LVivona/identicons/tree/main
Author: Luca Vivona
Author-email: lucavivona01@gmail.com
Classifier: Programming Language :: Python :: 3
Classifier: Programming Language :: Python :: 3.6
Classifier: Programming Language :: Python :: 3.7
Classifier: Programming Language :: Python :: 3.8
Classifier: Programming Language :: Python :: 3.9
Classifier: Programming Language :: Python :: 3.10
Classifier: Programming Language :: Python :: 3.11
Classifier: License :: OSI Approved :: MIT License
Classifier: Development Status :: 3 - Alpha
Classifier: Intended Audience :: Developers
Classifier: Topic :: Software Development :: Libraries :: Python Modules
Classifier: Operating System :: OS Independent
Classifier: Natural Language :: English
Classifier: Environment :: Console
Classifier: Topic :: Utilities
Requires-Dist: numpy >=1.13.3
Requires-Dist: rich >=13.6.0
